koya_aws/__init__.py
koya_aws/koya_aws.py
koya_aws-0.0.12.dist-info/LICENSE
koya_aws-0.0.12.dist-info/METADATA
koya_aws-0.0.12.dist-info/WHEEL
koya_aws-0.0.12.dist-info/top_level.txt
koya_aws-0.0.12.dist-info/RECORD
