Metadata-Version: 2.1
Name: koya-aws
Version: 0.0.12
Author: 
Author-email: 
License: MIT
Requires-Python: >=3.6
License-File: LICENSE
Requires-Dist: boto3
Requires-Dist: pandas
